{
 "museum1": [ 
   {"source": "MET",
             "url": "https://collectionapi.metmuseum.org/public/collection/v1/",
             "class": "MetMuseum", "key": "none" },
  {"source": "Rijsk",
             "url": "https://www.rijksmuseum.nl/api/en/",
             "class": "RijksMuseum", "key": "qvMYRE87" },
  {"source": "Cleveland",
             "url": "https://openaccess-api.clevelandart.org/api/artworks/",
             "class": "ClevelandMuseum", "key": "none" },
  {"source": "Europe",
             "url": "https://api.europeana.eu/api/v2/",
             "class": "EuropeMuseum", "key": "ixzop5MkY" },
  {"source": "Meise",
             "url": "https://api.europeana.eu/api/v2/",
             "class": "EuropeMuseum", "key": "ixzop5MkY", "dataprovider": "Meise+Botanic+Garden" },
  {"source": "Wienbibliothek",
             "url": "https://api.europeana.eu/api/v2/",
             "class": "EuropeMuseum", "key": "ixzop5MkY", "dataprovider": "Wienbibliothek+im+Rathaus" },
  {"source": "University of Graz",
             "url": "https://api.europeana.eu/api/v2/",
             "class": "EuropeMuseum", "key": "ixzop5MkY", "dataprovider": "University of Graz, Institute of Plant Sciences - Herbarium GZU" },
 {"source": "Smithsonian",
              "url": "https://api.si.edu/openaccess/api/v1.0/search", 
              "class": "SmithsonianMuseum", "key": "imQAjl1QkgYj0EiPybG1lKaz4dp0AZSauYCgPi3B"},
 {"source": "Paris",
                "url": "https://apicollections.parismusees.paris.fr/graphql",
                "class": "ParisMuseum", "key": "323ac194-f611-4583-9620-b5e9351f56ad"}
  ]
}
